twirp/__init__.py
twirp/asgi.py
twirp/async_client.py
twirp/base.py
twirp/client.py
twirp/context.py
twirp/ctxkeys.py
twirp/endpoint.py
twirp/errors.py
twirp/exceptions.py
twirp/hook.py
twirp/logging.py
twirp/py.typed
twirp/server.py
twirpy-0.3.0.dev2.dist-info/METADATA
twirpy-0.3.0.dev2.dist-info/WHEEL
twirpy-0.3.0.dev2.dist-info/licenses/LICENSE
twirpy-0.3.0.dev2.dist-info/RECORD
