Metadata-Version: 2.4
Name: twirpy
Version: 0.3.0.dev2
Summary: Twirp runtime library for Python
Project-URL: repository, https://github.com/cryptact/twirpy
License-Expression: BSD-3-Clause
License-File: LICENSE
Keywords: protobuf,rpc,twirp
Requires-Python: >=3.12
Requires-Dist: asgiref
Requires-Dist: protobuf
Requires-Dist: requests
Requires-Dist: structlog
Provides-Extra: async
Requires-Dist: aiohttp; extra == 'async'
